bips/__init__.py
bips/bip_notifs.py
bips-0.0.3.0.1.dist-info/LICENSE.txt
bips-0.0.3.0.1.dist-info/METADATA
bips-0.0.3.0.1.dist-info/WHEEL
bips-0.0.3.0.1.dist-info/top_level.txt
bips-0.0.3.0.1.dist-info/RECORD
