Metadata-Version: 2.1
Name: bips
Version: 0.0.3.0.1
Summary: to play out beeping sounds to trigger audio alerts
Author: mose_tucker_0159
Author-email: mose.tucker.0159@gmail.com
Keywords: python
Classifier: Development Status :: 1 - Planning
Classifier: Intended Audience :: End Users/Desktop
Classifier: Programming Language :: Python :: 3
Classifier: Operating System :: Microsoft :: Windows
Classifier: Operating System :: MacOS
License-File: LICENSE.txt
